torch_image_metrics/__init__.py
torch_image_metrics/calculator.py
torch_image_metrics/core/__init__.py
torch_image_metrics/core/base_metric.py
torch_image_metrics/core/data_structures.py
torch_image_metrics/evaluator.py
torch_image_metrics/metrics/__init__.py
torch_image_metrics/metrics/basic.py
torch_image_metrics/metrics/dataset.py
torch_image_metrics/metrics/perceptual.py
torch_image_metrics/utils/__init__.py
torch_image_metrics/utils/image_matcher.py
torch_image_metrics-0.1.0.dist-info/WHEEL
torch_image_metrics-0.1.0.dist-info/METADATA
torch_image_metrics-0.1.0.dist-info/RECORD
