Metadata-Version: 2.3
Name: torch-image-metrics
Version: 0.1.0
Summary: Unified PyTorch image quality metrics library
Author: Yus314
Author-email: Yus314 <shizhaoyoujie@gmail.com>
License: MIT
Classifier: Programming Language :: Python :: 3
Classifier: Programming Language :: Python :: 3.10
Classifier: Programming Language :: Python :: 3.11
Classifier: License :: OSI Approved :: MIT License
Classifier: Topic :: Scientific/Engineering :: Artificial Intelligence
Classifier: Topic :: Software Development :: Libraries :: Python Modules
Classifier: Intended Audience :: Developers
Classifier: Intended Audience :: Science/Research
Requires-Dist: torch>=2.0.0
Requires-Dist: torchvision>=0.15.0
Requires-Dist: pillow>=9.0.0
Requires-Dist: numpy>=1.21.0
Requires-Dist: tqdm>=4.67.1
Requires-Dist: pytest>=8.0.0 ; extra == 'dev'
Requires-Dist: pytest-mock>=3.14.0 ; extra == 'dev'
Requires-Dist: pytest-cov>=4.0.0 ; extra == 'dev'
Requires-Dist: ruff>=0.1.0 ; extra == 'dev'
Requires-Dist: mypy>=1.0.0 ; extra == 'dev'
Requires-Dist: lpips>=0.1.4 ; extra == 'full'
Requires-Dist: pytorch-fid>=0.3.0 ; extra == 'full'
Requires-Dist: torchmetrics>=1.8.2 ; extra == 'full'
Requires-Dist: scipy>=1.10.0 ; extra == 'full'
Requires-Python: >=3.10, <3.12
Project-URL: Documentation, https://github.com/mdipcit/torch-image-metrics#readme
Project-URL: Homepage, https://github.com/mdipcit/torch-image-metrics
Project-URL: Issues, https://github.com/mdipcit/torch-image-metrics/issues
Project-URL: Repository, https://github.com/mdipcit/torch-image-metrics
Provides-Extra: dev
Provides-Extra: full
